unitycatalog/ai/autogen/__init__.py
unitycatalog/ai/autogen/toolkit.py
unitycatalog/ai/autogen/version.py
unitycatalog_autogen-0.2.1.dist-info/METADATA
unitycatalog_autogen-0.2.1.dist-info/WHEEL
unitycatalog_autogen-0.2.1.dist-info/RECORD
