Metadata-Version: 2.4
Name: unitycatalog-autogen
Version: 0.2.1
Summary: Support for Unity Catalog functions as autogen tools
Author-email: Puneet Jain <puneet.jain@databricks.com>
License: Apache-2.0
Requires-Python: >=3.9
Requires-Dist: autogen-agentchat>=0.4.0
Requires-Dist: autogen-core>=0.4.0
Requires-Dist: openai>=1.46.1
Requires-Dist: pydantic<3,>=2
Requires-Dist: unitycatalog-ai
Provides-Extra: databricks
Requires-Dist: unitycatalog-ai[databricks]; extra == 'databricks'
Provides-Extra: databricks-dev
Requires-Dist: unitycatalog-ai[databricks-dev]; extra == 'databricks-dev'
Provides-Extra: dev
Requires-Dist: autogen-ext>=0.4.0; extra == 'dev'
Requires-Dist: unitycatalog-ai[dev]; extra == 'dev'
